moirai/__init__.py
moirai/__main__.py
moirai/abstract_process_handler.py
moirai/decorators.py
moirai/installer.py
moirai/moirai.py
moirai/database/__init__.py
moirai/database/mongodb.py
moirai/database/mysql.py
moirai/hardware/__init__.py
moirai/hardware/cmd_processor.py
moirai/hardware/configured_hardware.py
moirai/hardware/controller.py
moirai/hardware/free.py
moirai/hardware/model_simulation.py
moirai/hardware/pid.py
moirai/hardware/system_response_tests.py
moirai/hardware/timer.py
moirai/webapi/__init__.py
moirai/webapi/api.py
moirai/webapi/cmd_processor.py
moirai-1.3.31.dist-info/METADATA
moirai-1.3.31.dist-info/WHEEL
moirai-1.3.31.dist-info/entry_points.txt
moirai-1.3.31.dist-info/licenses/LICENSE
moirai-1.3.31.dist-info/RECORD
