Metadata-Version: 2.4
Name: moirai
Version: 1.3.31
Summary: Digital Control Manager Backend
Project-URL: Repository, https://github.com/acristoffers/moirai
Author-email: Álan Crístoffer <acristoffers@startmail.com>
License-Expression: MIT
License-File: LICENSE
Keywords: digital control manager
Requires-Python: <3.15,>=3.9
Requires-Dist: ahio~=1.0.33
Requires-Dist: appdirs<2,>=1.4.4
Requires-Dist: cheroot<11,>=10.0.0
Requires-Dist: flask<3,>=2.3.3
Requires-Dist: mysql-connector-python<9,>=8.0.33
Requires-Dist: numpy<2,>=1.26.2
Requires-Dist: pymongo<5,>=4.6.1
Requires-Dist: python-dateutil<3,>=2.8.2
Requires-Dist: scipy<2,>=1.11.4
